passiogo/__init__.py
tests/__init__.py
tests/test_main.py
PassioGo-0.2.1.dist-info/LICENSE
PassioGo-0.2.1.dist-info/METADATA
PassioGo-0.2.1.dist-info/WHEEL
PassioGo-0.2.1.dist-info/top_level.txt
PassioGo-0.2.1.dist-info/RECORD
