Metadata-Version: 2.1
Name: PassioGo
Version: 0.2.1
Summary: An unofficial API for Passio Go
Home-page: https://github.com/athuler/PassioGo
Author: Andrei Thuler
Author-email: info@andreithuler.com
License: UNKNOWN
Project-URL: Documentation, https://passiogo.readthedocs.io/
Project-URL: GitHub, https://github.com/athuler/PassioGo
Project-URL: Sponsor, https://github.com/sponsors/athuler
Project-URL: Changelog, https://github.com/athuler/PassioGo/blob/main/CHANGELOG.md
Platform: UNKNOWN
License-File: LICENSE
Requires-Dist: requests>=2.22.0
Requires-Dist: websocket-client>=1.2.0
